eticas/__init__.py
eticas/audit/__init__.py
eticas/audit/base_audit.py
eticas/audit/drift_audit.py
eticas/audit/labeled_audit.py
eticas/audit/unlabeled_audit.py
eticas/data/__init__.py
eticas/data/loaders.py
eticas/metrics/__init__.py
eticas/metrics/base_metric.py
eticas/metrics/d_calibrated.py
eticas/metrics/d_equalodds.py
eticas/metrics/d_parity.py
eticas/metrics/d_statisticalparity.py
eticas/metrics/da_fairness.py
eticas/metrics/da_inconsistency.py
eticas/metrics/da_informative.py
eticas/metrics/da_positive.py
eticas/metrics/disparate_impact.py
eticas/metrics/dxa_inconsistency.py
eticas/metrics/performance.py
eticas/metrics/tdx_inconsistency.py
eticas/model/__init__.py
eticas/model/base_model.py
eticas/model/ml_model.py
eticas/utils/__init__.py
eticas/utils/api.py
eticas/utils/helpers.py
eticas_audit-0.1.7.dist-info/licenses/LICENSE
eticas_audit-0.1.7.dist-info/METADATA
eticas_audit-0.1.7.dist-info/WHEEL
eticas_audit-0.1.7.dist-info/top_level.txt
eticas_audit-0.1.7.dist-info/RECORD
