Metadata-Version: 2.4
Name: eticas-audit
Version: 0.1.7
Summary: An open-source Python library designed for developers to calculate fairness metrics and assess bias in machine learning models.
Home-page: https://github.com/eticasai/eticas-audit
Author: Eticas AI
Author-email: Eticas AI <it@eticas.ai>
License: Apache-2.0
Requires-Python: >=3.11.9
License-File: LICENSE
Requires-Dist: numpy==2.1.2
Requires-Dist: pandas==2.2.3
Requires-Dist: scikit-learn==1.5.2
Requires-Dist: pyarrow==19.0.0
Requires-Dist: scipy==1.15.1
Requires-Dist: coverage==7.6.10
Requires-Dist: requests==2.32.3
Dynamic: author
Dynamic: home-page
Dynamic: license-file
Dynamic: requires-dist
